{"ret":1,"msg":"succ","data":{"admin_name":"sheji","gData":{"action":"sys","opt":"editPermission","act":"pm","pmid":"2","sessionid":"gmd5hdaetbqk9f21k04emqtjt1","lastPage":"setid_grouplist"},"menuData":[{"1":{"id":"1","name":"\u8d26\u6237\u603b\u89c8","route":"overview","backend":"[{\"path\": \"gdtadput/ret_ads_config\"}, {\"path\": \"gdtadput/targeting_tags\"}, {\"path\": \"sys/get_user_memo\"}]","order":"0","state":"1","list":{"2":{"id":"2","name":"\u8d26\u6237\u603b\u89c8","route":"overview/home_index","backend":"[{\"path\": \"sys/get_messages\"}, {\"path\": \"sys/index\"}, {\"path\": \"bdadput/bindAccount\"}, {\"path\": \"ucadput/bindAccount\"}, {\"path\": \"sys/authMedia\"}, {\"path\": \"api/getMedia\"}, {\"path\": \"api/getAuthor\"}, {\"path\": \"sys/getAgent\"}, {\"path\": \"ttadput/getAuthorizedUrl\"}]","order":"0","state":"1","acstate":0}},"acstate":0},"3":{"id":"3","name":"\u5e7f\u70b9\u901a\u5b9e\u65f6\u6295\u653e","route":"time","backend":"[{\"path\": \"sys/set_user_memo\"}]","order":"0","state":"1","list":{"4":{"id":"4","name":"\u5b9e\u65f6\u6295\u653e\u8ba1\u5212","route":"time/time_plan","backend":"[{\"path\": \"gdtadput/campaigns_add\"}, {\"path\": \"api/getCampaigns\"}, {\"path\": \"api/getAccount\"}, {\"path\": \"gdtadput/campaigns\"}, {\"path\": \"api/getAuthor\"}, {\"path\": \"api/getGameLists\"}]","order":"0","state":"1","acstate":0},"5":{"id":"5","name":"\u5b9e\u65f6\u6295\u653e\u5e7f\u544a","route":"time/time_ad","backend":"[{\"path\": \"gdtadput/getCam\"}, {\"path\": \"gdtadput/updateAdGroup\"}, {\"path\": \"gdtadput/getAdGroup\"}, {\"path\": \"gdtadput/checkProductUrl\"}, {\"path\": \"gdtadput/adgroupGet\"}, {\"path\": \"gdtadput/adcreativeGet\"}, {\"path\": \"gdtadput/getImageById\"}, {\"path\": \"api/getCreatives\"}, {\"path\": \"gdtadput/adcre_add\"}, {\"path\": \"gdtadput/ads_cre_add\"}, {\"path\": \"gdtadput/targetings\"}, {\"path\": \"gdtadput/init_targetings\"}, {\"path\": \"gdtadput/targetings_add\"}, {\"path\": \"gdtadput/adcreatives_doadd\"}, {\"path\": \"gdtadput/adcreatives_del\"}, {\"path\": \"gdtadput/adsimg\"}, {\"path\": \"gdtadput/addImage\"}, {\"path\": \"gdtadput/adsVideo_doadd\"}, {\"path\": \"gdtadput/products_add\"}, {\"path\": \"gdtadput/products_doupdate\"}, {\"path\": \"gdtadput/ads_doadd\"}, {\"path\": \"gdtadput/ads_status_update\"}, {\"path\": \"gdtadput/ads_doupdate\"}, {\"path\": \"gdtadput/ads_del\"}, {\"path\": \"gdtadput/get_estimation\"}, {\"path\": \"api/getTargetings\"}, {\"path\": \"gdtadput/custom_audiences_get\"}, {\"path\": \"gdtadput/products_info_get\"}, {\"path\": \"api/getAdgroups\"}, {\"path\": \"gdtadput/getAdgroupTemplateId\"}, {\"path\": \"gdtadput/get_adgroup_detail\"}, {\"path\": \"api/getCampaigns\"}, {\"path\": \"gdtadput/adgroups\"}, {\"path\": \"gdtadput/adgroups_add\"}, {\"path\": \"api/getAccount\"}, {\"path\": \"api/getAuthor\"}, {\"path\": \"api/getGameLists\"}]","order":"0","state":"1","acstate":0},"6":{"id":"6","name":"\u8d22\u52a1","route":"time/time_finance","backend":null,"order":"0","state":"1","list":{"7":{"id":"7","name":"\u8d44\u91d1\u6d41\u6c34","route":"time/time_finance/time_journal","backend":"[{\"path\": \"gdtaccount/fund_statements_detailed_download\"}, {\"path\": \"gdtaccount/fund_statements_detailed\"}, {\"path\": \"api/getAccount\"}]","order":"0","state":"1","acstate":0},"8":{"id":"8","name":"\u8d22\u52a1\u4fe1\u606f","route":"time/time_finance/time_funds","backend":"[{\"path\": \"gdtaccount/funds_get\"}, {\"path\": \"api/getAccount\"}]","order":"0","state":"1","acstate":0},"9":{"id":"9","name":"\u5145\u503c\u8bb0\u5f55","route":"time/time_finance/time_rechargeRecord","backend":"[{\"path\": \"sys/accountRechargeDel\"}, {\"path\": \"sys/updateAccountRecharge\"}, {\"path\": \"sys/getAdsAthour\"}, {\"path\": \"sys/accountRechargeData\"}, {\"path\": \"api/getAuthor\"}, {\"path\": \"sys/getAgent\"}]","order":"0","state":"1","acstate":0},"10":{"id":"10","name":"\u8f6c\u5e10\u8bb0\u5f55","route":"time/time_finance/time_transferAccounts","backend":"[{\"path\": \"sys/DeleteAccountTransfer\"}, {\"path\": \"sys/accountTransferData\"}, {\"path\": \"api/getAuthor\"}, {\"path\": \"sys/getAgent\"}]","order":"0","state":"1","acstate":0}},"acstate":0}},"acstate":0},"11":{"id":"11","name":"UC\u5b9e\u65f6\u6295\u653e","route":"uc","backend":null,"order":"0","state":"1","list":{"12":{"id":"12","name":"\u63a8\u5e7f\u7ba1\u7406","route":"uc/uc_advertiser","backend":"[{\"path\": \"api/getAuthor\"}, {\"path\": \"api/getAccount\"}, {\"path\": \"ucadput/getAccount\"}, {\"path\": \"ucadput/updateCreativePaused\"}, {\"path\": \"ucadput/updateCreativeName\"}, {\"path\": \"ucadput/updateAdgroupBidByPercentage\"}, {\"path\": \"ucadput/updateAdgroupNetworkEnv\"}, {\"path\": \"ucadput/updateAdgroupRegion\"}, {\"path\": \"ucadput/updateAdgroupPaused\"}, {\"path\": \"ucadput/updateAdgroupBid\"}, {\"path\": \"ucadput/updateAdgroupName\"}, {\"path\": \"ucadput/updateCampaignPaused\"}, {\"path\": \"ucadput/updateCampaignDate\"}, {\"path\": \"ucadput/updateCampaignBudget\"}, {\"path\": \"ucadput/updateCampaignName\"}, {\"path\": \"ucadput/getAllCreativeTemplates\"}, {\"path\": \"ucadput/getIosAppByAppId\"}, {\"path\": \"ucadput/getAndroidApps\"}, {\"path\": \"ucadput/getWordPackage\"}, {\"path\": \"ucadput/getRecommend\"}, {\"path\": \"ucadput/getAppCategory\"}, {\"path\": \"ucadput/getInterest\"}, {\"path\": \"ucadput/getCreativeTemplates\"}, {\"path\": \"ucadput/getCounty\"}, {\"path\": \"ucadput/getProvince\"}, {\"path\": \"ucadput/getAdConvert\"}, {\"path\": \"ucadput/getConvertType\"}, {\"path\": \"ucadput/searchCreatives\"}, {\"path\": \"ucadput/searchAdgroups\"}, {\"path\": \"ucadput/searchCampaigns\"}, {\"path\": \"ttadput/getTargetingList\"}, {\"path\": \"ucadput/updateTargeting\"}, {\"path\": \"ucadput/getAdgroupById\"}, {\"path\": \"ucadput/getCreativeById\"}, {\"path\": \"ucadput/updateCreative\"}, {\"path\": \"ucadput/updateAdgroup\"}, {\"path\": \"ucadput/updateCampaign\"}, {\"path\": \"ucadput/deleteCreative\"}, {\"path\": \"ucadput/deleteAdgroup\"}, {\"path\": \"ucadput/deleteCampaign\"}, {\"path\": \"ucadput/adsimg_doadd\"}, {\"path\": \"ucadput/getCampaignNameList\"}, {\"path\": \"ucadput/getAdgroupNameList\"}, {\"path\": \"ucadput/getTargetingList\"}, {\"path\": \"ucadput/getAdgroupsList\"}, {\"path\": \"ucadput/getCampaignsList\"}, {\"path\": \"ucadput/addTargeting\"}, {\"path\": \"ucadput/addCreative\"}, {\"path\": \"ucadput/addAdgroup\"}, {\"path\": \"ucadput/addCampaign\"}]","order":"0","state":"1","list":{"13":{"id":"13","name":"\u63a8\u5e7f\u8ba1\u5212","route":"uc/uc_advertiser/uc_plan","backend":null,"order":"0","state":"1","acstate":0},"14":{"id":"14","name":"\u63a8\u5e7f\u5355\u5143","route":"uc/uc_advertiser/uc_unit","backend":null,"order":"0","state":"1","acstate":0},"15":{"id":"15","name":"\u521b\u610f","route":"uc/uc_advertiser/uc_creativity","backend":null,"order":"0","state":"1","acstate":0}},"acstate":0},"16":{"id":"16","name":"\u6570\u636e\u62a5\u544a","route":"uc/uc_report","backend":"[{\"path\": \"ucadput/getAudienceReporting\"}, {\"path\": \"ucadput/getProvinceReporting\"}, {\"path\": \"ucadput/getGradationReporting\"}, {\"path\": \"ucadput/getHourReporting\"}, {\"path\": \"ucadput/getAppReporting\"}, {\"path\": \"ucadput/getAdresourceReporting\"}, {\"path\": \"api/getAuthor\"}, {\"path\": \"api/getAccount\"}, {\"path\": \"ucadput/getAccount\"}]","order":"0","state":"1","acstate":0},"17":{"id":"17","name":"\u8d22\u52a1","route":"uc/uc_finance","backend":null,"order":"0","state":"1","list":{"18":{"id":"18","name":"\u5145\u503c\u8bb0\u5f55","route":"uc/uc_finance/uc_rechargeRecord","backend":"[{\"path\": \"sys/updateAccountRecharge\"}, {\"path\": \"sys/getAgent\"}, {\"path\": \"sys/accountRechargeChange\"}, {\"path\": \"sys/accountRechargeDel\"}, {\"path\": \"sys/accountRechargeData\"}, {\"path\": \"sys/accountRecharge\"}]","order":"0","state":"1","acstate":0},"19":{"id":"19","name":"\u8f6c\u5e10\u8bb0\u5f55","route":"uc/uc_finance/uc_transferAccounts","backend":"[{\"path\": \"sys/DeleteAccountTransfer\"}, {\"path\": \"api/getAccountByAgent\"}, {\"path\": \"sys/accountTransfer\"}, {\"path\": \"sys/accountTransferData\"}]","order":"0","state":"1","acstate":0}},"acstate":0}},"acstate":0},"20":{"id":"20","name":"\u4eca\u65e5\u5934\u6761\u6295\u653e","route":"tt","backend":null,"order":"0","state":"1","list":{"21":{"id":"21","name":"\u63a8\u5e7f\u7ba1\u7406","route":"tt/tt_advertiser","backend":"[{\"path\": \"ttadput/getConvertList\"}, {\"path\": \"ttadput/updateTargeting\"}, {\"path\": \"ttadput/createInterestWord\"}, {\"path\": \"ttadput/getAudienceArticle\"}, {\"path\": \"ttadput/getPhone\"}, {\"path\": \"ttadput/getInterestWord\"}, {\"path\": \"ttadput/getAppType\"}, {\"path\": \"ttadput/getTag\"}, {\"path\": \"ttadput/getProvince\"}, {\"path\": \"ttadput/getTargetingDetail\"}, {\"path\": \"ttadput/addTargeting\"}, {\"path\": \"ttadput/getTargetingList\"}, {\"path\": \"ttadput/getImages\"}, {\"path\": \"ttadput/getCreativeWords\"}, {\"path\": \"ttadput/addVideo\"}, {\"path\": \"ttadput/addImage\"}, {\"path\": \"ttadput/getCreativeCategory\"}, {\"path\": \"ttadput/getCreativesByAdgroupId\"}, {\"path\": \"ttadput/getCreatives\"}, {\"path\": \"ttadput/updateCreativeStatus\"}, {\"path\": \"ttadput/judgeCreative\"}, {\"path\": \"ttadput/searchCreatives\"}, {\"path\": \"ttadput/updateAdgroupName\"}, {\"path\": \"ttadput/getAdgroups\"}, {\"path\": \"ttadput/updateAdgroupBid\"}, {\"path\": \"ttadput/updateAdgroupBudget\"}, {\"path\": \"ttadput/updateAdgroupStatus\"}, {\"path\": \"ttadput/updateAdgroup\"}, {\"path\": \"ttadput/addAdgroup\"}, {\"path\": \"ttadput/searchAdgroups\"}, {\"path\": \"ttadput/getCampaigns\"}, {\"path\": \"ttadput/updateCampaignStatus\"}, {\"path\": \"ttadput/updateCampaign\"}, {\"path\": \"ttadput/addCampaign\"}, {\"path\": \"ttadput/searchCampaigns\"}]","order":"0","state":"1","list":{"22":{"id":"22","name":"\u5e7f\u544a\u7ec4","route":"tt/tt_advertiser/tt_campaign","backend":null,"order":"0","state":"1","acstate":0},"23":{"id":"23","name":"\u5e7f\u544a\u8ba1\u5212","route":"tt/tt_advertiser/tt_ad","backend":null,"order":"0","state":"1","acstate":0},"24":{"id":"24","name":"\u521b\u610f","route":"tt/tt_advertiser/tt_creative","backend":null,"order":"0","state":"1","acstate":0}},"acstate":0},"25":{"id":"25","name":"\u6570\u636e\u62a5\u544a","route":"tt/tt_report","backend":"[{\"path\": \"ttadput/effectAdcreativeReporting\"}, {\"path\": \"ttadput/effectAdgroupReporting\"}, {\"path\": \"ttadput/effectCampaignReporting\"}, {\"path\": \"ttadput/audienceAdgroupReporting\"}, {\"path\": \"ttadput/audienceAdgroupReportingChart\"}, {\"path\": \"ttadput/audienceCampaignReportingChart\"}, {\"path\": \"ttadput/audienceCampaignReporting\"}, {\"path\": \"ttadput/audienceReportingChart\"}, {\"path\": \"ttadput/audienceAccountReporting\"}, {\"path\": \"ttadput/accountReporting\"}]","order":"0","state":"1","list":{"26":{"id":"26","name":"\u8d26\u6237\u62a5\u8868","route":"tt/tt_report/tt_statement","backend":null,"order":"0","state":"1","acstate":0},"27":{"id":"27","name":"\u53d7\u4f17\u5206\u6790","route":"tt/tt_report/tt_audience","backend":null,"order":"0","state":"1","acstate":0},"28":{"id":"28","name":"\u6548\u679c\u5e7f\u544a\u62a5\u8868","route":"tt/tt_report/tt_bid","backend":null,"order":"0","state":"1","acstate":0}},"acstate":0},"29":{"id":"29","name":"\u8d22\u52a1","route":"tt/tt_finance","backend":null,"order":"0","state":"1","list":{"30":{"id":"30","name":"\u5145\u503c\u8bb0\u5f55","route":"tt/tt_finance/tt_rechargeRecord","backend":"[{\"path\": \"sys/updateAccountRecharge\"}, {\"path\": \"sys/getAgent\"}, {\"path\": \"sys/accountRechargeChange\"}, {\"path\": \"sys/accountRechargeDel\"}, {\"path\": \"sys/accountRechargeData\"}, {\"path\": \"sys/accountRecharge\"}]","order":"0","state":"1","acstate":0},"31":{"id":"31","name":"\u8f6c\u5e10\u8bb0\u5f55","route":"tt/tt_finance/tt_transferAccounts","backend":"[{\"path\": \"sys/DeleteAccountTransfer\"}, {\"path\": \"api/getAccountByAgent\"}, {\"path\": \"sys/accountTransfer\"}, {\"path\": \"sys/accountTransferData\"}]","order":"0","state":"1","acstate":0},"57":{"id":"57","name":"\u8d44\u91d1\u6d41\u6c34","route":"tt/tt_finance/tt_funds","backend":"[{\"path\": \"ttadput/getAccountFund\"}]","order":"0","state":"1","acstate":3}},"acstate":0}},"acstate":0},"32":{"id":"32","name":"\u767e\u5ea6\u6295\u653e","route":"bd","backend":null,"order":"0","state":"1","list":{"33":{"id":"33","name":"\u9996\u9875","route":"bd/bd_main","backend":null,"order":"0","state":"1","acstate":0},"34":{"id":"34","name":"\u63a8\u5e7f\u7ba1\u7406","route":"bd/bd_advertiser","backend":null,"order":"0","state":"1","list":{"35":{"id":"35","name":"\u63a8\u5e7f\u8ba1\u5212","route":"bd/bd_advertiser/bd_campaign","backend":"[{\"path\": \"bdadput/searchCampaigns\"}]","order":"0","state":"1","acstate":0},"36":{"id":"36","name":"\u63a8\u5e7f\u5355\u5143","route":"bd/bd_advertiser/bd_adgroup","backend":"[{\"path\": \"bdadput/searchAdgroups\"}]","order":"0","state":"1","acstate":0},"37":{"id":"37","name":"\u63a8\u5e7f\u521b\u610f","route":"bd/bd_advertiser/bd_creative","backend":"[{\"path\": \"bdadput/searchCreatives\"}]","order":"0","state":"1","acstate":0}},"acstate":0}},"acstate":0},"38":{"id":"38","name":"\u6e20\u9053\u4fe1\u606f","route":"channel","backend":"[{\"path\": \"api/getAccount\"}, {\"path\": \"api/getGameLists\"}, {\"path\": \"api/getMedia\"}, {\"path\": \"api/getAuthor\"}]","order":"0","state":"1","list":{"39":{"id":"39","name":"\u4ea7\u54c1\u603b\u89c8","route":"channel/channel_product","backend":"[{\"path\": \"api/getGameTotalDay\"}]","order":"0","state":"1","acstate":0},"40":{"id":"40","name":"\u5a92\u4f53\u603b\u89c8","route":"channel/channel_media","backend":"[{\"path\": \"api/getGameTotalDay\"}]","order":"0","state":"1","acstate":0},"41":{"id":"41","name":"\u8d26\u6237\u603b\u89c8","route":"channel/channel_account","backend":"[{\"path\": \"api/getGameTotalDay\"}]","order":"0","state":"1","acstate":0},"42":{"id":"42","name":"\u8ba1\u5212\u603b\u89c8","route":"channel/channel_plan","backend":"[{\"path\": \"api/getGameTotalDay\"}, {\"path\": \"api/getCampaigns\"}]","order":"0","state":"1","acstate":0},"43":{"id":"43","name":"\u5e7f\u544a\u603b\u89c8","route":"channel/channel_ad","backend":"[{\"path\": \"api/getGameTotalDay\"}, {\"path\": \"api/getCampaigns\"}]","order":"0","state":"1","acstate":0}},"acstate":0},"44":{"id":"44","name":"\u8d26\u53f7\u7ba1\u7406","route":"setid","backend":"[]","order":"0","state":"1","list":{"45":{"id":"45","name":"\u4fee\u6539\u4e2a\u4eba\u4fe1\u606f","route":"setid/setid_modprfpsw","backend":"[{\"path\": \"sys/getPositions\"}, {\"path\": \"sys/editUser\"}]","order":"0","state":"1","acstate":0},"46":{"id":"46","name":"\u8d26\u53f7\u7ba1\u7406","route":"setid/setid_userlist","backend":"[{\"path\": \"sys/getPositions\"}, {\"path\": \"sys/getDepartments\"}, {\"path\": \"sys/showUser\"}, {\"path\": \"sys/editPermission\"}, {\"path\": \"sys/userEdit\"}]","order":"0","state":"1","acstate":0},"47":{"id":"47","name":"\u6743\u9650\u7ec4\u7ba1\u7406","route":"setid/setid_grouplist","backend":"[{\"path\": \"sys/editPermission\"}, {\"path\": \"sys/pmgroup\"}]","order":"0","state":"1","acstate":0},"48":{"id":"48","name":"\u8d26\u6237\u65e5\u5fd7","route":"setid/setid_userlog","backend":"[{\"path\": \"sys/logs\"}]","order":"0","state":"1","acstate":0},"49":{"id":"49","name":"\u8d1f\u8d23\u4eba\u7ba1\u7406","route":"setid/setid_principal","backend":"[{\"path\": \"sys/getAdsAthour\"}, {\"path\": \"sys/getAdsAccount\"}, {\"path\": \"sys/AdsAccountAdd\"}, {\"path\": \"sys/updateAdsAccount\"}]","order":"0","state":"1","acstate":0},"50":{"id":"50","name":"\u7cfb\u7edf\u8d26\u53f7\u7ba1\u7406","route":"setid/setid_systemsetid","backend":"[{\"path\": \"sys/getInCharge\"}, {\"path\": \"sys/getMedia\"}, {\"path\": \"sys/getAgent\"}, {\"path\": \"sys/mutilEditAcPermission\"}, {\"path\": \"sys/accountList\"}]","order":"0","state":"1","acstate":0},"51":{"id":"51","name":"\u7cfb\u7edf\u6d88\u606f","route":"setid/setid_systemmsg","backend":"[{\"path\": \"sys/get_messages\"}]","order":"0","state":"1","acstate":0},"56":{"id":"56","name":"\u83dc\u5355\u7ba1\u7406","route":"setid/setid_menu","backend":"[{\"path\": \"sys/editPageBackendApis\"}, {\"path\": \"sys/getActionList\"}, {\"path\": \"sys/getMenus\"}, {\"path\": \"sys/permissionCache\"}, {\"path\": \"sys/addMenu\"}]","order":"0","state":"1","acstate":0},"59":{"id":"59","name":"\u7cfb\u7edf\u8d26\u53f7\u6743\u9650\u7ba1\u7406","route":"setid/setid_systemstatussetid","backend":"[{\"path\": \"sys/getAdsAthour\"}, {\"path\": \"sys/userAcGrant\"}, {\"path\": \"sys/userAcGrantInfo\"}]","order":"0","state":"1","acstate":0}},"acstate":0}}]}}